tkoneflow/__init__.py
tkoneflow-0.1.0.dist-info/METADATA
tkoneflow-0.1.0.dist-info/WHEEL
tkoneflow-0.1.0.dist-info/entry_points.txt
tkoneflow-0.1.0.dist-info/RECORD
