Metadata-Version: 2.1
Name: tkoneflow
Version: 0.1.0
Summary: Lime CRM package
Author: Author
Author-email: author@lime.tech
Requires-Python: >=3.11,<4.0
Classifier: Programming Language :: Python :: 3
Classifier: Programming Language :: Python :: 3.11
Classifier: Programming Language :: Python :: 3.12
Classifier: Programming Language :: Python :: 3.13
Requires-Dist: lime-crm (>=2.526.0,<3.0.0)
Requires-Dist: limepkg-getaccept (>=1.3.12,<2.0.0)
Requires-Dist: limepkg-scrive (>=2.1.6,<3.0.0)
